{"errors":["./src/components/ContactForm.jsx\nModule build failed (from ./node_modules/gatsby/dist/utils/babel-loader.js):\nSyntaxError: C:\\Users\\Hayden\\Desktop\\Deadhead Design\\deadheadesign\\src\\components\\ContactForm.jsx: Unexpected token (15:4)\n\n\u001b[0m \u001b[90m 13 | \u001b[39m  \u001b[36mconst\u001b[39m onSubmit \u001b[33m=\u001b[39m data \u001b[33m=>\u001b[39m {\u001b[0m\n\u001b[0m \u001b[90m 14 | \u001b[39m    console\u001b[33m.\u001b[39mlog(data)\u001b[33m;\u001b[39m\u001b[0m\n\u001b[0m\u001b[31m\u001b[1m>\u001b[22m\u001b[m\u001b[39m\u001b[90m 15 | \u001b[39m    )\u001b[33m;\u001b[39m\u001b[0m\n\u001b[0m \u001b[90m    | \u001b[39m    \u001b[31m\u001b[1m^\u001b[22m\u001b[m\u001b[39m\u001b[0m\n\u001b[0m \u001b[90m 16 | \u001b[39m  }\u001b[33m;\u001b[39m\u001b[0m\n\u001b[0m \u001b[90m 17 | \u001b[39m\u001b[0m\n\u001b[0m \u001b[90m 18 | \u001b[39m  \u001b[36mreturn\u001b[39m (\u001b[0m\n    at Object._raise (C:\\Users\\Hayden\\Desktop\\Deadhead Design\\deadheadesign\\node_modules\\@babel\\parser\\src\\parser\\error.js:60:45)\n    at Object.raiseWithData (C:\\Users\\Hayden\\Desktop\\Deadhead Design\\deadheadesign\\node_modules\\@babel\\parser\\src\\parser\\error.js:55:17)\n    at Object.raise (C:\\Users\\Hayden\\Desktop\\Deadhead Design\\deadheadesign\\node_modules\\@babel\\parser\\src\\parser\\error.js:39:17)\n    at Object.unexpected (C:\\Users\\Hayden\\Desktop\\Deadhead Design\\deadheadesign\\node_modules\\@babel\\parser\\src\\parser\\util.js:139:16)\n    at Object.parseExprAtom (C:\\Users\\Hayden\\Desktop\\Deadhead Design\\deadheadesign\\node_modules\\@babel\\parser\\src\\parser\\expression.js:1186:20)\n    at Object.parseExprAtom (C:\\Users\\Hayden\\Desktop\\Deadhead Design\\deadheadesign\\node_modules\\@babel\\parser\\src\\plugins\\jsx\\index.js:535:22)\n    at Object.parseExprSubscripts (C:\\Users\\Hayden\\Desktop\\Deadhead Design\\deadheadesign\\node_modules\\@babel\\parser\\src\\parser\\expression.js:563:23)\n    at Object.parseUpdate (C:\\Users\\Hayden\\Desktop\\Deadhead Design\\deadheadesign\\node_modules\\@babel\\parser\\src\\parser\\expression.js:543:21)\n    at Object.parseMaybeUnary (C:\\Users\\Hayden\\Desktop\\Deadhead Design\\deadheadesign\\node_modules\\@babel\\parser\\src\\parser\\expression.js:527:17)\n    at Object.parseExprOps (C:\\Users\\Hayden\\Desktop\\Deadhead Design\\deadheadesign\\node_modules\\@babel\\parser\\src\\parser\\expression.js:343:23)\n    at Object.parseMaybeConditional (C:\\Users\\Hayden\\Desktop\\Deadhead Design\\deadheadesign\\node_modules\\@babel\\parser\\src\\parser\\expression.js:308:23)\n    at Object.parseMaybeAssign (C:\\Users\\Hayden\\Desktop\\Deadhead Design\\deadheadesign\\node_modules\\@babel\\parser\\src\\parser\\expression.js:263:21)\n    at Object.parseExpressionBase (C:\\Users\\Hayden\\Desktop\\Deadhead Design\\deadheadesign\\node_modules\\@babel\\parser\\src\\parser\\expression.js:183:23)\n    at callback (C:\\Users\\Hayden\\Desktop\\Deadhead Design\\deadheadesign\\node_modules\\@babel\\parser\\src\\parser\\expression.js:176:39)\n    at Object.allowInAnd (C:\\Users\\Hayden\\Desktop\\Deadhead Design\\deadheadesign\\node_modules\\@babel\\parser\\src\\parser\\expression.js:2622:12)\n    at Object.parseExpression (C:\\Users\\Hayden\\Desktop\\Deadhead Design\\deadheadesign\\node_modules\\@babel\\parser\\src\\parser\\expression.js:176:17)"],"warnings":[],"namedChunkGroups":{"polyfill":{"chunks":[0,9],"assets":["webpack-runtime-484fa639b0c31c6a368e.js","webpack-runtime-484fa639b0c31c6a368e.js.map","polyfill-79c10299cbaaf6b93565.js","polyfill-79c10299cbaaf6b93565.js.map"],"children":{},"childAssets":{}},"app":{"chunks":[0,10,8,1],"assets":["webpack-runtime-484fa639b0c31c6a368e.js","webpack-runtime-484fa639b0c31c6a368e.js.map","styles.abe12935b70d962fec0b.css","styles-755093da0c07f4b49226.js","styles-755093da0c07f4b49226.js.map","framework-e2d419ac45d8ae41957a.js","framework-e2d419ac45d8ae41957a.js.map","app-e8d110aeceea2f4419ce.js","app-e8d110aeceea2f4419ce.js.map"],"children":{},"childAssets":{}},"component---src-pages-404-js":{"chunks":[2],"assets":["component---src-pages-404-js-b3ccd0571c739d45a952.js","component---src-pages-404-js-b3ccd0571c739d45a952.js.map"],"children":{},"childAssets":{}},"component---src-pages-about-js":{"chunks":[3],"assets":["component---src-pages-about-js-0431f138b4dfbc405515.js","component---src-pages-about-js-0431f138b4dfbc405515.js.map"],"children":{},"childAssets":{}},"component---src-pages-contact-js":{"chunks":[4],"assets":["component---src-pages-contact-js-a3fbc37916f34a7b80a1.js","component---src-pages-contact-js-a3fbc37916f34a7b80a1.js.map"],"children":{},"childAssets":{}},"component---src-pages-index-js":{"chunks":[5],"assets":["component---src-pages-index-js-5d2d74bd44f332b6f930.js","component---src-pages-index-js-5d2d74bd44f332b6f930.js.map"],"children":{},"childAssets":{}},"component---src-pages-portfolio-js":{"chunks":[6],"assets":["component---src-pages-portfolio-js-663120075a5779a49637.js","component---src-pages-portfolio-js-663120075a5779a49637.js.map"],"children":{},"childAssets":{}},"component---src-pages-services-js":{"chunks":[7],"assets":["component---src-pages-services-js-69a24485f0597bfc097b.js","component---src-pages-services-js-69a24485f0597bfc097b.js.map"],"children":{},"childAssets":{}}},"assetsByChunkName":{"polyfill":["webpack-runtime-484fa639b0c31c6a368e.js","polyfill-79c10299cbaaf6b93565.js"],"app":["webpack-runtime-484fa639b0c31c6a368e.js","styles.abe12935b70d962fec0b.css","styles-755093da0c07f4b49226.js","framework-e2d419ac45d8ae41957a.js","app-e8d110aeceea2f4419ce.js"],"component---src-pages-404-js":["component---src-pages-404-js-b3ccd0571c739d45a952.js"],"component---src-pages-about-js":["component---src-pages-about-js-0431f138b4dfbc405515.js"],"component---src-pages-contact-js":["component---src-pages-contact-js-a3fbc37916f34a7b80a1.js"],"component---src-pages-index-js":["component---src-pages-index-js-5d2d74bd44f332b6f930.js"],"component---src-pages-portfolio-js":["component---src-pages-portfolio-js-663120075a5779a49637.js"],"component---src-pages-services-js":["component---src-pages-services-js-69a24485f0597bfc097b.js"]}}